datapyx/__init__.py
datapyx/pack.py
datapyx-0.0.3.dist-info/METADATA
datapyx-0.0.3.dist-info/WHEEL
datapyx-0.0.3.dist-info/top_level.txt
datapyx-0.0.3.dist-info/RECORD
