Metadata-Version: 2.1
Name: datapyx
Version: 0.0.3
Summary: Short stat snippets
Author: Bency Dsouza
